movici_viewer/__init__.py
movici_viewer/caching.py
movici_viewer/dependencies.py
movici_viewer/exceptions.py
movici_viewer/main.py
movici_viewer/model/__init__.py
movici_viewer/model/file_info.py
movici_viewer/model/model.py
movici_viewer/routers/__init__.py
movici_viewer/routers/datasets.py
movici_viewer/routers/scenarios.py
movici_viewer/routers/static.py
movici_viewer/routers/updates.py
movici_viewer/routers/views.py
movici_viewer/schemas/__init__.py
movici_viewer/schemas/dataset.py
movici_viewer/schemas/scenario.py
movici_viewer/schemas/summary.py
movici_viewer/schemas/update.py
movici_viewer/schemas/view.py
movici_viewer/settings.py
movici_viewer/ui/assets/basedecoder-B2c5_Eok.js
movici_viewer/ui/assets/deflate-B9JhHpvg.js
movici_viewer/ui/assets/index-C-VtZ6J0.js
movici_viewer/ui/assets/index-CJUi40WM.css
movici_viewer/ui/assets/jpeg-vtRboCKw.js
movici_viewer/ui/assets/lerc-4y23M84i.js
movici_viewer/ui/assets/lzw-_aCqfs4w.js
movici_viewer/ui/assets/movici_logo-DGV2v5gu.svg
movici_viewer/ui/assets/movici_symbol-DiNQeDKB.svg
movici_viewer/ui/assets/packbits-DDWKfGV_.js
movici_viewer/ui/assets/pako.esm-Cram60i4.js
movici_viewer/ui/assets/raw-in9isEBO.js
movici_viewer/ui/assets/webimage-DBgUwIbt.js
movici_viewer/ui/favicon.ico
movici_viewer/ui/index.html
movici_viewer/ui/static/basemaps/dark.png
movici_viewer/ui/static/basemaps/light.png
movici_viewer/ui/static/basemaps/satellite.png
movici_viewer/ui/static/basemaps/streets.png
movici_viewer/ui/static/icons/icons.png
movici_viewer/ui/static/icons/shapes.png
movici_viewer/ui/static/movici-flow.png
movici_viewer/ui/static/movici-flow.svg
movici_viewer/ui/static/movici-logo.svg
movici_viewer/ui/static/no-project.png
movici_viewer/ui/static/no-resources.png
movici_viewer-1.1.0.dist-info/METADATA
movici_viewer-1.1.0.dist-info/WHEEL
movici_viewer-1.1.0.dist-info/entry_points.txt
movici_viewer-1.1.0.dist-info/RECORD
