Metadata-Version: 2.4
Name: movici-viewer
Version: 1.1.0
Summary: Modern web-based visualization platform for Movici geospatial simulations
License: Movici Public License
Keywords: geospatial,visualization,simulation,fastapi,vue,gis
Author: NGinfra Movici
Author-email: movici@nginfra.nl
Maintainer: NGinfra Movici
Maintainer-email: movici@nginfra.nl
Requires-Python: >=3.11
Classifier: Development Status :: 4 - Beta
Classifier: Intended Audience :: Science/Research
Classifier: Intended Audience :: Developers
Classifier: License :: Free for non-commercial use
Classifier: License :: Other/Proprietary License
Classifier: Operating System :: Microsoft :: Windows
Classifier: Operating System :: POSIX :: Linux
Classifier: Programming Language :: Python
Classifier: Programming Language :: Python :: 3.11
Classifier: Programming Language :: Python :: 3.12
Classifier: Programming Language :: Python :: 3.13
Classifier: Programming Language :: Python :: 3 :: Only
Classifier: Topic :: Scientific/Engineering :: GIS
Provides-Extra: dev
Requires-Dist: click (>=8)
Requires-Dist: fastapi
Requires-Dist: httpx ; extra == "dev"
Requires-Dist: movici-simulation-core[models] (>=2.11)
Requires-Dist: orjson
Requires-Dist: pydantic
Requires-Dist: pydantic_settings
Requires-Dist: pytest ; extra == "dev"
Requires-Dist: ruff ; extra == "dev"
Requires-Dist: taplo ; extra == "dev"
Requires-Dist: uvicorn[standard]
